README.md
setup.py
configs/__init__.py
multi_emotion/__init__.py
multi_emotion/multi_emotion.py
multi_emotion.egg-info/PKG-INFO
multi_emotion.egg-info/SOURCES.txt
multi_emotion.egg-info/dependency_links.txt
multi_emotion.egg-info/requires.txt
multi_emotion.egg-info/top_level.txt
multi_emotion/data/__init__.py
multi_emotion/data/data.py
multi_emotion/model/__init__.py
multi_emotion/model/attention.py
multi_emotion/model/base_model.py
multi_emotion/model/lm.py
multi_emotion/utils/__init__.py
multi_emotion/utils/callbacks.py
multi_emotion/utils/conf.py
multi_emotion/utils/data.py
multi_emotion/utils/logging.py
multi_emotion/utils/losses.py
multi_emotion/utils/metrics.py
multi_emotion/utils/optim.py
multi_emotion/utils/utils.py
multi_emotion/utils/sentiTree/__init__.py
multi_emotion/utils/sentiTree/data_utils.py