Metadata-Version: 2.1
Name: multi-emotion
Version: 0.1.15
Summary: detect multiple emotions in a sentence including [anger, anticipation, disgust, fear, joy, love, optimism, pessimism, sadness,                    surprise, trust]
Home-page: https://github.com/JinfenLi/multi_emotion_recognition
Author: Jinfen Li
Author-email: jli284@syr.edu
License: MIT
Classifier: Programming Language :: Python :: 3
Classifier: License :: OSI Approved :: Apache Software License
Classifier: Programming Language :: Python :: 3.9
Requires-Dist: lightning>=2
Requires-Dist: emotlib
Requires-Dist: numpy
Requires-Dist: pandas
Requires-Dist: rich
Requires-Dist: torchmetrics>=1
